[
  {
    "name": "chat-topbar",
    "dependencies": [
      "@radix-ui/react-avatar",
      "lucide-react",
      "@/lib/utils"
    ],
    "files": [
      {
        "name": "chat-topbar.tsx",
        "content": "import React from 'react'\nimport { Avatar, AvatarImage } from '../ui/avatar'\nimport { UserData } from '@/app/data';\nimport { Info, Phone, Video } from 'lucide-react';\nimport Link from 'next/link';\nimport { cn } from '@/lib/utils';\nimport { buttonVariants } from '../ui/button';\n\ninterface ChatTopbarProps {\n  selectedUser: UserData;\n}\n\nexport const TopbarIcons = [{ icon: Phone }, { icon: Video }, { icon: Info }];\n\nexport default function ChatTopbar({ selectedUser }: ChatTopbarProps) {\n  return (\n    <div className=\"w-full h-20 flex p-4 justify-between items-center border-b\">\n      <div className=\"flex items-center gap-2\">\n        <Avatar className=\"flex justify-center items-center\">\n          <AvatarImage\n            src={selectedUser.avatar}\n            alt={selectedUser.name}\n            width={6}\n            height={6}\n            className=\"w-10 h-10 \"\n          />\n        </Avatar>\n        <div className=\"flex flex-col\">\n          <span className=\"font-medium\">{selectedUser.name}</span>\n          <span className=\"text-xs\">Active 2 mins ago</span>\n        </div>\n      </div>\n\n      <div>\n        {TopbarIcons.map((icon, index) => (\n          <Link\n            key={index}\n            href=\"#\"\n            className={cn(\n              buttonVariants({ variant: \"ghost\", size: \"icon\" }),\n              \"h-9 w-9\",\n              \"dark:bg-muted dark:text-muted-foreground dark:hover:bg-muted dark:hover:text-white\"\n            )}\n          >\n            <icon.icon size={20} className=\"text-muted-foreground\" />\n          </Link>\n        ))}\n      </div>\n    </div>\n  )\n}"
      }
    ],
    "type": "components:ui"
  }
]